marbl/__init__.py
marbl/cli.py
marbl/combinations.py
marbl/dataset.py
marbl/main.py
marbl/matrix_context.py
marbl/model.py
marbl/pileup.py
marbl/predict.py
marbl/py.typed
marbl/variant_sites.py
marbl/vcf_utils.py
marbl_pool-0.6.0.dist-info/METADATA
marbl_pool-0.6.0.dist-info/WHEEL
marbl_pool-0.6.0.dist-info/entry_points.txt
marbl_pool-0.6.0.dist-info/licenses/LICENSE
marbl_pool-0.6.0.dist-info/RECORD
