Metadata-Version: 2.4
Name: marbl-pool
Version: 0.6.0
Summary: Matrix assignment of rare variants using bayesian logic.
Project-URL: Homepage, https://github.com/madscort/marbl
Project-URL: Repository, https://github.com/madscort/marbl.git
Project-URL: Issues, https://github.com/madscort/marbl/issues
Author-email: Mads Nielsen <madsn@msn.com>
License: MIT License
License-File: LICENSE
Classifier: Development Status :: 3 - Alpha
Classifier: Intended Audience :: Science/Research
Classifier: License :: OSI Approved :: MIT License
Classifier: Programming Language :: Python :: 3
Classifier: Programming Language :: Python :: 3.11
Classifier: Programming Language :: Python :: 3.12
Classifier: Topic :: Scientific/Engineering :: Bio-Informatics
Requires-Python: >=3.11
Requires-Dist: pandas<3,>=2.3.2
Requires-Dist: pysam<0.24,>=0.23.3
Requires-Dist: scipy<2,>=1.16.1
Requires-Dist: tqdm<5,>=4.67.1
Provides-Extra: dev
Requires-Dist: pytest-cov>=4.0; extra == 'dev'
Requires-Dist: pytest>=7.0; extra == 'dev'
Requires-Dist: ruff>=0.1.0; extra == 'dev'
